{"lastUsed":1605839364762,"path":"C:\/Repositorios\/IA-Learning-to-Drive","projectCount":1,"recentFiles":[{"path":"\/agoravai\/src\/environment","parentWorkspace":"C:\/Repositorios\/IA-Learning-to-Drive","name":"Car.java","lastModified":1605839212094,"locationURI":"file:\/C:\/Repositorios\/IA-Learning-to-Drive\/agoravai\/src\/environment\/Car.java"},{"path":"\/agoravai\/src\/ai","parentWorkspace":"C:\/Repositorios\/IA-Learning-to-Drive","name":"WaveFront.java","lastModified":1605839212094,"locationURI":"file:\/C:\/Repositorios\/IA-Learning-to-Drive\/agoravai\/src\/ai\/WaveFront.java"},{"path":"\/agoravai\/src\/application","parentWorkspace":"C:\/Repositorios\/IA-Learning-to-Drive","name":"main.fxml","lastModified":1605839211884,"locationURI":"file:\/C:\/Repositorios\/IA-Learning-to-Drive\/agoravai\/src\/application\/main.fxml"},{"path":"\/agoravai\/src\/environment","parentWorkspace":"C:\/Repositorios\/IA-Learning-to-Drive","name":"Sensors.java","lastModified":1605828328922,"locationURI":"file:\/C:\/Repositorios\/IA-Learning-to-Drive\/agoravai\/src\/environment\/Sensors.java"},{"path":"\/agoravai\/src\/application","parentWorkspace":"C:\/Repositorios\/IA-Learning-to-Drive","name":"Controller.java","lastModified":1605839212094,"locationURI":"file:\/C:\/Repositorios\/IA-Learning-to-Drive\/agoravai\/src\/application\/Controller.java"},{"path":"\/agoravai\/src\/ai","parentWorkspace":"C:\/Repositorios\/IA-Learning-to-Drive","name":"NeuralNetwork.java","lastModified":1605697222181,"locationURI":"file:\/C:\/Repositorios\/IA-Learning-to-Drive\/agoravai\/src\/ai\/NeuralNetwork.java"},{"path":"\/agoravai\/src\/ai","parentWorkspace":"C:\/Repositorios\/IA-Learning-to-Drive","name":"EvolutionAlgorithm.java","lastModified":1605839212093,"locationURI":"file:\/C:\/Repositorios\/IA-Learning-to-Drive\/agoravai\/src\/ai\/EvolutionAlgorithm.java"},{"path":"\/agoravai\/src\/application","parentWorkspace":"C:\/Repositorios\/IA-Learning-to-Drive","name":"Main.java","lastModified":1605836696561,"locationURI":"file:\/C:\/Repositorios\/IA-Learning-to-Drive\/agoravai\/src\/application\/Main.java"},{"path":"\/agoravai\/src\/application","parentWorkspace":"C:\/Repositorios\/IA-Learning-to-Drive","name":"mainController.java","lastModified":1605839364833,"locationURI":"file:\/C:\/Repositorios\/IA-Learning-to-Drive\/agoravai\/src\/application\/mainController.java"},{"path":"\/agoravai\/src\/environment","parentWorkspace":"C:\/Repositorios\/IA-Learning-to-Drive","name":"Collider.java","lastModified":1605829001706,"locationURI":"file:\/C:\/Repositorios\/IA-Learning-to-Drive\/agoravai\/src\/environment\/Collider.java"},{"path":"\/agoravai\/src\/ai","parentWorkspace":"C:\/Repositorios\/IA-Learning-to-Drive","name":"Nodes.java","lastModified":1605378082597,"locationURI":"file:\/C:\/Repositorios\/IA-Learning-to-Drive\/agoravai\/src\/ai\/Nodes.java"}]}